traderfit_bridge/__init__.py
traderfit_bridge/main.py
traderfit_bridge-0.2.9.dist-info/METADATA
traderfit_bridge-0.2.9.dist-info/WHEEL
traderfit_bridge-0.2.9.dist-info/entry_points.txt
traderfit_bridge-0.2.9.dist-info/top_level.txt
traderfit_bridge-0.2.9.dist-info/RECORD
