Metadata-Version: 2.4
Name: traderfit-bridge
Version: 0.2.9
Summary: A stdio bridge for the TraderFit MCP API
Author-email: Kisra Fistya <kisra.fistya@gmail.com>
Project-URL: Homepage, https://github.com/rizkisyaf/traderfit-bridge
Project-URL: Bug Tracker, https://github.com/rizkisyaf/traderfit-bridge/issues
Classifier: Programming Language :: Python :: 3
Classifier: License :: OSI Approved :: MIT License
Classifier: Operating System :: OS Independent
Requires-Python: >=3.9
Requires-Dist: mcp>=1.6.0
Requires-Dist: httpx>=0.25.0
Requires-Dist: python-dotenv>=1.0.0
Requires-Dist: openapi-pydantic>=0.5.0
